{
  "_doc": "Edit this list and run: npm run catalog:scrape-sf -- --input ./scripts/catalog-sources-sketchfab.example.json --out ./catalog-import.json --per-query 6 --limit 200",
  "queries": [
    { "query": "modern sofa", "tags": "furniture" },
    { "query": "l-shape sectional sofa", "tags": "furniture" },
    { "query": "armchair lounge", "tags": "furniture" },
    { "query": "king size bed", "tags": "furniture" },
    { "query": "queen storage bed", "tags": "furniture" },
    { "query": "modern wardrobe", "tags": "furniture" },
    { "query": "sliding wardrobe", "tags": "furniture" },
    { "query": "nightstand bedside", "tags": "furniture" },
    { "query": "dining table 6 seater", "tags": "furniture" },
    { "query": "dining chair upholstered", "tags": "furniture" },
    { "query": "round coffee table wood", "tags": "furniture" },
    { "query": "marble coffee table", "tags": "furniture" },
    { "query": "tv unit wall mounted", "tags": "furniture" },
    { "query": "bookshelf modern", "tags": "furniture" },
    { "query": "console table", "tags": "furniture" },
    { "query": "kitchen base cabinet modular", "tags": "furniture" },
    { "query": "kitchen wall cabinet", "tags": "furniture" },
    { "query": "kitchen pantry tall unit" },
    { "query": "kitchen sink stainless steel" },
    { "query": "chimney hood kitchen" },
    { "query": "refrigerator double door" },
    { "query": "double sink vanity" },
    { "query": "floating bathroom vanity" },
    { "query": "wall hung toilet" },
    { "query": "shower glass enclosure" },
    { "query": "freestanding bathtub" },
    { "query": "ergonomic office chair" },
    { "query": "standing desk adjustable" },
    { "query": "executive desk wood" },
    { "query": "bunk bed kids" },
    { "query": "kids study unit" },
    { "query": "pendant light cluster", "tags": "lighting" },
    { "query": "chandelier modern", "tags": "lighting" },
    { "query": "floor lamp arc", "tags": "lighting" },
    { "query": "table lamp ceramic", "tags": "lighting" },
    { "query": "ceiling fan with light" },
    { "query": "fiddle leaf fig plant", "tags": "decor" },
    { "query": "monstera plant pot" },
    { "query": "abstract wall art canvas" },
    { "query": "throw pillow set linen" },
    { "query": "decorative vase tall" },
    { "query": "balcony swing jhula" },
    { "query": "outdoor lounge chair" },
    { "query": "indian cane lounge chair" },
    { "query": "scandinavian dining chair wishbone" }
  ]
}
